total_time_formatter/__init__.py
total_time_formatter/formatter.py
total_time_formatter-1.0.5.dist-info/licenses/LICENSE
total_time_formatter-1.0.5.dist-info/METADATA
total_time_formatter-1.0.5.dist-info/WHEEL
total_time_formatter-1.0.5.dist-info/top_level.txt
total_time_formatter-1.0.5.dist-info/RECORD
