Metadata-Version: 2.4
Name: total-time-formatter
Version: 1.0.5
Summary: A flexible library to convert various time inputs into a total duration format (HH:MM:SS).
Author-email: Cibelle Maciel da Costa <cibellemaciel02@gmail.com>
License: # LICENSE
Project-URL: Homepage, https://github.com/cibellemc/total-time-formatter/
Project-URL: Bug Tracker, https://github.com/cibellemc/total-time-formatter/issues
Keywords: datetime,timedelta,formatter,time,duration,hours,precision
Classifier: Development Status :: 5 - Production/Stable
Classifier: Intended Audience :: Developers
Classifier: License :: OSI Approved :: MIT License
Classifier: Operating System :: OS Independent
Classifier: Programming Language :: Python :: 3
Classifier: Programming Language :: Python :: 3.7
Classifier: Programming Language :: Python :: 3.8
Classifier: Programming Language :: Python :: 3.9
Classifier: Programming Language :: Python :: 3.10
Classifier: Programming Language :: Python :: 3.11
Classifier: Programming Language :: Python :: 3.12
Classifier: Topic :: Software Development :: Libraries :: Python Modules
Classifier: Topic :: Utilities
Requires-Python: >=3.7
License-File: LICENSE
Requires-Dist: pandas
Requires-Dist: openpyxl
Dynamic: license-file
